README.txt
bootstrap.py
buildout.cfg
setup.cfg
setup.py
docs/HISTORY.txt
docs/INSTALL.txt
docs/LICENSE.GPL
docs/LICENSE.txt
ely/__init__.py
ely.portlets.image.egg-info/PKG-INFO
ely.portlets.image.egg-info/SOURCES.txt
ely.portlets.image.egg-info/dependency_links.txt
ely.portlets.image.egg-info/entry_points.txt
ely.portlets.image.egg-info/namespace_packages.txt
ely.portlets.image.egg-info/not-zip-safe
ely.portlets.image.egg-info/requires.txt
ely.portlets.image.egg-info/top_level.txt
ely/portlets/__init__.py
ely/portlets/image/__init__.py
ely/portlets/image/configure.zcml
ely/portlets/image/image.py
ely/portlets/image/imageportlet.pt
ely/portlets/image/imageportlet.py
ely/portlets/image/imageview.py
ely/portlets/image/inputwidget.pt
ely/portlets/image/interfaces.py
ely/portlets/image/version.txt
ely/portlets/image/widget.py
ely/portlets/image/profiles/default/metadata.xml
ely/portlets/image/profiles/default/portlets.xml
ely/portlets/image/tests/__init__.py
ely/portlets/image/tests/base.py
ely/portlets/image/tests/test_image.jpg
ely/portlets/image/tests/test_portlet.py