Metadata-Version: 1.0
Name: ely.portlets.image
Version: 0.4
Summary: A portlet for attaching and linking a single image
Home-page: http://code.google.com/p/ely/source/browse
Author: Matt Halstead
Author-email: matt@elyt.com
License: GPL
Keywords: plone portlet image
Platform: UNKNOWN
Classifier: Framework :: Plone
Classifier: Programming Language :: Python
Classifier: Topic :: Software Development :: Libraries :: Python Modules
